imapmail.py
imapmail_mod-0.0.1.dist-info/LICENSE
imapmail_mod-0.0.1.dist-info/METADATA
imapmail_mod-0.0.1.dist-info/WHEEL
imapmail_mod-0.0.1.dist-info/top_level.txt
imapmail_mod-0.0.1.dist-info/RECORD
