Metadata-Version: 2.1
Name: imapmail-mod
Version: 0.0.1
Summary: A module for doing imap
Home-page: https://github.com/ejohnfel/imapmail
Author: Eric Johnfelt
Author-email: ejohnfel@hotmail.com
License: UNKNOWN
Project-URL: Bug Tracker, https://github.com/ejohnfel/imapmail/issues
Platform: UNKNOWN
Classifier: Programming Language :: Python :: 3
Classifier: License :: OSI Approved :: MIT License
Classifier: Operating System :: OS Independent
Requires-Python: >=3.8
License-File: LICENSE
